image_caption_scraper/__init__.py
image_caption_scraper/expansion.py
image_caption_scraper/helper.py
image_caption_scraper/scraper.py
image_caption_scraper-0.0.3.dist-info/LICENSE
image_caption_scraper-0.0.3.dist-info/METADATA
image_caption_scraper-0.0.3.dist-info/WHEEL
image_caption_scraper-0.0.3.dist-info/top_level.txt
image_caption_scraper-0.0.3.dist-info/RECORD
