Metadata-Version: 2.1
Name: image_caption_scraper
Version: 0.0.3
Summary: image-caption-scraper is a Python tool for downloading images and captions from image search engines.
Home-page: https://github.com/alishibli97/image-caption-scraper
Author: Ali Shibli
Author-email: alishibli97@hotmail.com
Project-URL: Bug Tracker, https://github.com/alishibli97/image-caption-scraper/issues
Classifier: Programming Language :: Python :: 3
Classifier: License :: OSI Approved :: MIT License
Classifier: Operating System :: OS Independent
Requires-Python: >=3.11
License-File: LICENSE
